odoo/addons/fieldservice_delivery/README.rst
odoo/addons/fieldservice_delivery/__init__.py
odoo/addons/fieldservice_delivery/__manifest__.py
odoo/addons/fieldservice_delivery/i18n/de.po
odoo/addons/fieldservice_delivery/i18n/es.po
odoo/addons/fieldservice_delivery/i18n/es_AR.po
odoo/addons/fieldservice_delivery/i18n/es_CL.po
odoo/addons/fieldservice_delivery/i18n/fieldservice_delivery.pot
odoo/addons/fieldservice_delivery/i18n/it.po
odoo/addons/fieldservice_delivery/i18n/pt_BR.po
odoo/addons/fieldservice_delivery/models/__init__.py
odoo/addons/fieldservice_delivery/models/fsm_order.py
odoo/addons/fieldservice_delivery/models/stock.py
odoo/addons/fieldservice_delivery/readme/CONFIGURE.rst
odoo/addons/fieldservice_delivery/readme/CONTRIBUTORS.rst
odoo/addons/fieldservice_delivery/readme/CREDITS.rst
odoo/addons/fieldservice_delivery/readme/DESCRIPTION.rst
odoo/addons/fieldservice_delivery/readme/INSTALL.rst
odoo/addons/fieldservice_delivery/readme/ROADMAP.rst
odoo/addons/fieldservice_delivery/readme/USAGE.rst
odoo/addons/fieldservice_delivery/static/description/icon.png
odoo/addons/fieldservice_delivery/static/description/index.html
odoo/addons/fieldservice_delivery/tests/__init__.py
odoo/addons/fieldservice_delivery/tests/test_fsm_delivery.py
odoo/addons/fieldservice_delivery/views/fsm_order.xml
odoo_addon_fieldservice_delivery-15.0.1.0.1.dist-info/METADATA
odoo_addon_fieldservice_delivery-15.0.1.0.1.dist-info/WHEEL
odoo_addon_fieldservice_delivery-15.0.1.0.1.dist-info/top_level.txt
odoo_addon_fieldservice_delivery-15.0.1.0.1.dist-info/RECORD
