Metadata-Version: 2.1
Name: odoo-addon-fieldservice_delivery
Version: 15.0.1.0.1
Summary: Select delivery methods and carriers on Field Service orders
Home-page: https://github.com/OCA/field-service
Author: Open Source Integrators, Odoo Community Association (OCA)
Author-email: support@odoo-community.org
License: AGPL-3
Classifier: Programming Language :: Python
Classifier: Framework :: Odoo
Classifier: Framework :: Odoo :: 15.0
Classifier: License :: OSI Approved :: GNU Affero General Public License v3
Classifier: Development Status :: 4 - Beta
Requires-Python: >=3.8
Requires-Dist: odoo-addon-fieldservice-stock<15.1dev,>=15.0dev
Requires-Dist: odoo-addon-stock-request<15.1dev,>=15.0dev
Requires-Dist: odoo<15.1dev,>=15.0a
